aion/__init__.py
aion/cli.py
aion/code.py
aion/embed.py
aion/evaluate.py
aion/files.py
aion/git.py
aion/maths.py
aion/parser.py
aion/pdf.py
aion/prompt.py
aion/snippets.py
aion/test_files.py
aion/text.py
aion/utils.py
aion/watcher.py
aqwel_aion-0.1.7.dist-info/licenses/LICENSE
aqwel_aion-0.1.7.dist-info/METADATA
aqwel_aion-0.1.7.dist-info/WHEEL
aqwel_aion-0.1.7.dist-info/top_level.txt
aqwel_aion-0.1.7.dist-info/RECORD
