Metadata-Version: 2.4
Name: aqwel-aion
Version: 0.1.7
Summary: 🚀 Aqwel-Aion v0.1.7 — Complete AI Research & Development Library with Advanced Mathematics and ML Tools
Home-page: https://aqwelai.com/#aqwel-aion
Author: Aksel Aghajanyan
Author-email: Aksel Aghajanyan <aqwelaiofficial@gmail.com>
Project-URL: Homepage, https://aqwelai.com/#aqwel-aion
Project-URL: PyPI, https://pypi.org/project/aqwel-aion/
Keywords: ai-research,machine-learning,mathematics,statistics,data-science,embeddings,aqwel-ai
Classifier: Development Status :: 4 - Beta
Classifier: Intended Audience :: Developers
Classifier: Operating System :: OS Independent
Classifier: Programming Language :: Python :: 3
Classifier: Programming Language :: Python :: 3.8
Classifier: Programming Language :: Python :: 3.9
Classifier: Programming Language :: Python :: 3.10
Classifier: Programming Language :: Python :: 3.11
Classifier: Programming Language :: Python :: 3.12
Classifier: Topic :: Software Development :: Libraries :: Python Modules
Classifier: Topic :: Text Processing
Classifier: Topic :: Utilities
Requires-Python: >=3.8
License-File: LICENSE
Requires-Dist: numpy>=1.21.0
Requires-Dist: watchdog>=2.1.0
Requires-Dist: gitpython>=3.1.0
Provides-Extra: dev
Requires-Dist: pytest>=6.0; extra == "dev"
Requires-Dist: black>=21.0; extra == "dev"
Requires-Dist: flake8>=3.8; extra == "dev"
Provides-Extra: ai
Requires-Dist: scipy>=1.7.0; extra == "ai"
Requires-Dist: scikit-learn>=1.0.0; extra == "ai"
Requires-Dist: pandas>=1.3.0; extra == "ai"
Requires-Dist: matplotlib>=3.5.0; extra == "ai"
Requires-Dist: transformers>=4.20.0; extra == "ai"
Requires-Dist: torch>=1.12.0; extra == "ai"
Requires-Dist: openai>=1.0.0; extra == "ai"
Requires-Dist: sentence-transformers>=2.2.0; extra == "ai"
Provides-Extra: docs
Requires-Dist: reportlab>=3.6.0; extra == "docs"
Requires-Dist: pillow>=8.0.0; extra == "docs"
Provides-Extra: full
Requires-Dist: scipy>=1.7.0; extra == "full"
Requires-Dist: scikit-learn>=1.0.0; extra == "full"
Requires-Dist: pandas>=1.3.0; extra == "full"
Requires-Dist: matplotlib>=3.5.0; extra == "full"
Requires-Dist: seaborn>=0.11.0; extra == "full"
Requires-Dist: transformers>=4.20.0; extra == "full"
Requires-Dist: torch>=1.12.0; extra == "full"
Requires-Dist: openai>=1.0.0; extra == "full"
Requires-Dist: faiss-cpu>=1.7.0; extra == "full"
Requires-Dist: sentence-transformers>=2.2.0; extra == "full"
Requires-Dist: reportlab>=3.6.0; extra == "full"
Requires-Dist: pillow>=8.0.0; extra == "full"
Dynamic: author
Dynamic: home-page
Dynamic: license-file
Dynamic: requires-python
